Workbook

Sheet Assumptions
A1: The Coca-Cola Company (KO) — Assumptions
A3: Scenario | B3: Base | C3: Bear | D3: Base | E3: Bull
A4: Assumption | B4: Active | C4: Bear | D4: Base | E4: Bull
A5: INCOME STATEMENT
A6: Revenue Growth 2026F | B6: =IF($B$3="Bear",C6,IF($B$3="Base",D6,E6)) -> 0.05 | C6: 0.04 | D6: 0.05 | E6: 0.06
A7: Revenue Growth 2027F | B7: =IF($B$3="Bear",C7,IF($B$3="Base",D7,E7)) -> 0.05 | C7: 0.04 | D7: 0.05 | E7: 0.06
A8: Gross Margin % | B8: =IF($B$3="Bear",C8,IF($B$3="Base",D8,E8)) -> 0.615 | C8: 0.6 | D8: 0.615 | E8: 0.625
A9: SG&A % of Revenue | B9: =IF($B$3="Bear",C9,IF($B$3="Base",D9,E9)) -> 0.305 | C9: 0.315 | D9: 0.305 | E9: 0.295
A10: Effective Tax Rate | B10: =IF($B$3="Bear",C10,IF($B$3="Base",D10,E10)) -> 0.185 | C10: 0.2 | D10: 0.185 | E10: 0.175
A11: Dividend Payout Ratio | B11: =IF($B$3="Bear",C11,IF($B$3="Base",D11,E11)) -> 0.75 | C11: 0.8 | D11: 0.75 | E11: 0.7
A12: PP&E SCHEDULE
A13: CapEx % of Revenue | B13: =IF($B$3="Bear",C13,IF($B$3="Base",D13,E13)) -> 0.044 | C13: 0.047 | D13: 0.044 | E13: 0.04
A14: Depreciation Rate | B14: =IF($B$3="Bear",C14,IF($B$3="Base",D14,E14)) -> 0.11 | C14: 0.11 | D14: 0.11 | E14: 0.11
A15: WORKING CAPITAL
A16: DSO (days) | B16: =IF($B$3="Bear",C16,IF($B$3="Base",D16,E16)) -> 35 | C16: 38 | D16: 35 | E16: 32
A17: DIO (days) | B17: =IF($B$3="Bear",C17,IF($B$3="Base",D17,E17)) -> 37 | C17: 40 | D17: 37 | E17: 34
A18: DPO (days) | B18: =IF($B$3="Bear",C18,IF($B$3="Base",D18,E18)) -> 300 | C18: 290 | D18: 300 | E18: 315
A19: DEBT SCHEDULE
A20: Annual Debt Repayment ($m) | B20: =IF($B$3="Bear",C20,IF($B$3="Base",D20,E20)) -> 5000 | C20: 4000 | D20: 5000 | E20: 6000
A21: Interest Rate on Debt | B21: =IF($B$3="Bear",C21,IF($B$3="Base",D21,E21)) -> 0.036 | C21: 0.038 | D21: 0.036 | E21: 0.034
A22: Blue = editable | Black = formula | USD millions | Select scenario in B3

Sheet Model
A1: The Coca-Cola Company (KO) — Integrated 3-Statement Model ($ millions)
A2: Blue = hardcoded input | Black = formula | Forecast driven by Assumptions tab | Fiscal year end: December 31 | Currency: USD
C3: 2022A | D3: 2023A | E3: 2024A | F3: 2025A | G3: 2026F | H3: 2027F
A4: INCOME STATEMENT
A6: Revenue | C6: 43004 | D6: 45754 | E6: 47061 | F6: 47941 | G6: =F6*(1+Assumptions!B6) -> 50338.05 | H6: =G6*(1+Assumptions!B7) -> 52854.952
A8: Cost of Goods Sold (COGS) | C8: -18000 | D8: -18520 | E8: -18324 | F8: -18397 | G8: =-(G6*(1-Assumptions!B8)) -> -19380.149 | H8: =-(H6*(1-Assumptions!B8)) -> -20349.157
A10: Gross Profit | C10: =C6+C8 -> 25004 | D10: =D6+D8 -> 27234 | E10: =E6+E8 -> 28737 | F10: =F6+F8 -> 29544 | G10: =G6+G8 -> 30957.901 | H10: =H6+H8 -> 32505.796
A11: Gross Margin % | C11: =C10/C6 -> 0.58143429 | D11: =D10/D6 -> 0.59522665 | E11: =E10/E6 -> 0.61063301 | F11: =F10/F6 -> 0.61625748 | G11: =G10/G6 -> 0.615 | H11: =H10/H6 -> 0.615
A13: Operating Expenses
A15: Selling, General & Administrative (SG&A) | C15: -12880 | D15: -13972 | E15: -14582 | F15: -14521 | G15: =-(G6*Assumptions!B9) -> -15353.105 | H15: =-(H6*Assumptions!B9) -> -16120.761
A16: Research & Development | C16: 0 | D16: 0 | E16: 0 | F16: 0 | G16: 0 | H16: 0
A17: Other Operating Income / (Expense) | C17: -1215 | D17: -1951 | E17: -4163 | F17: -1261 | G17: 0 | H17: 0
A18: Total Operating Expenses | C18: =C15+C16+C17 -> -14095 | D18: =D15+D16+D17 -> -15923 | E18: =E15+E16+E17 -> -18745 | F18: =F15+F16+F17 -> -15782 | G18: =G15+G16+G17 -> -15353.105 | H18: =H15+H16+H17 -> -16120.761
A20: EBITDA | C20: =C10+C18 -> 10909 | D20: =D10+D18 -> 11311 | E20: =E10+E18 -> 9992 | F20: =F10+F18 -> 13762 | G20: =G10+G18 -> 15604.796 | H20: =H10+H18 -> 16385.035
A21: EBITDA Margin % | C21: =C20/C6 -> 0.25367408 | D21: =D20/D6 -> 0.24721336 | E21: =E20/E6 -> 0.21232018 | F21: =F20/F6 -> 0.28706118 | G21: =G20/G6 -> 0.31 | H21: =H20/H6 -> 0.31
A23: Depreciation & Amortisation (from PP&E Schedule) | C23: =C55 -> -1260 | D23: =D55 -> -1128 | E23: =E55 -> -1075 | F23: =F55 -> -1050 | G23: =G55 -> -1057.43 | H23: =H55 -> -1184.7489
A25: EBIT | C25: =C20+C23 -> 9649 | D25: =D20+D23 -> 10183 | E25: =E20+E23 -> 8917 | F25: =F20+F23 -> 12712 | G25: =G20+G23 -> 14547.365 | H25: =H20+H23 -> 15200.286
A26: EBIT Margin % | C26: =C25/C6 -> 0.22437448 | D26: =D25/D6 -> 0.22255978 | E26: =E25/E6 -> 0.18947749 | F26: =F25/F6 -> 0.26515926 | G26: =G25/G6 -> 0.28899343 | H26: =H25/H6 -> 0.2875849
A28: Below the Line
A30: Interest Expense (from Debt Schedule) | C30: -882 | D30: -1527 | E30: -1656 | F30: -1654 | G30: =G69 -> -1426.284 | H30: =H69 -> -1246.284
A31: Associates & Other Non-Operating | C31: 1210 | D31: 2261 | E31: 3762 | F31: 3104 | G31: =F31 -> 3104 | H31: =G31 -> 3104
A33: Profit Before Tax (PBT) | C33: =C25+C30+C31 -> 9977 | D33: =D25+D30+D31 -> 10917 | E33: =E25+E30+E31 -> 11023 | F33: =F25+F30+F31 -> 14162 | G33: =G25+G30+G31 -> 16225.082 | H33: =H25+H30+H31 -> 17058.002
A34: Tax Expense | C34: -2115 | D34: -2249 | E34: -2437 | F34: -2861 | G34: =-(G33*Assumptions!B10) -> -3001.6401 | H34: =-(H33*Assumptions!B10) -> -3155.7304
A36: NET PROFIT | C36: =C33+C34 -> 7862 | D36: =D33+D34 -> 8668 | E36: =E33+E34 -> 8586 | F36: =F33+F34 -> 11301 | G36: =G33+G34 -> 13223.441 | H36: =H33+H34 -> 13902.272
A37: Net Profit Margin % | C37: =C36/C6 -> 0.1828202 | D37: =D36/D6 -> 0.18944792 | E37: =E36/E6 -> 0.18244406 | F37: =F36/F6 -> 0.23572725 | G37: =G36/G6 -> 0.26269276 | H37: =H36/H6 -> 0.26302686
A39: Per Share
A41: Shares Outstanding (millions) | C41: 4350 | D41: 4339 | E41: 4320 | F41: 4313 | G41: 4313 | H41: 4313
A42: Earnings Per Share (EPS $) | C42: =C36/C41 -> 1.8073563 | D42: =D36/D41 -> 1.9976953 | E42: =E36/E41 -> 1.9875 | F42: =F36/F41 -> 2.6202179 | G42: =G36/G41 -> 3.0659498 | H42: =H36/H41 -> 3.2233415
A43: Dividend Per Share (DPS $) | C43: 1.76 | D43: 1.84 | E43: 1.94 | F43: 2.04 | G43: =G42*Assumptions!B11 -> 2.2994623 | H43: =H42*Assumptions!B11 -> 2.4175061
A45: Growth Rates
A47: Revenue Growth % | D47: =IFERROR(D6/C6-1,0) -> 0.06394754 | E47: =IFERROR(E6/D6-1,0) -> 0.028565808 | F47: =IFERROR(F6/E6-1,0) -> 0.018699135 | G47: =IFERROR(G6/F6-1,0) -> 0.05 | H47: =IFERROR(H6/G6-1,0) -> 0.05
A48: EBITDA Growth % | D48: =IFERROR(D20/C20-1,0) -> 0.036850307 | E48: =IFERROR(E20/D20-1,0) -> -0.11661215 | F48: =IFERROR(F20/E20-1,0) -> 0.37730184 | G48: =IFERROR(G20/F20-1,0) -> 0.13390463 | H48: =IFERROR(H20/G20-1,0) -> 0.05
A49: Net Profit Growth % | D49: =IFERROR(D36/C36-1,0) -> 0.10251844 | E49: =IFERROR(E36/D36-1,0) -> -0.0094600831 | F49: =IFERROR(F36/E36-1,0) -> 0.31621244 | G49: =IFERROR(G36/F36-1,0) -> 0.17011251 | H49: =IFERROR(H36/G36-1,0) -> 0.051335392
A51: PP&E SCHEDULE
A53: Opening Gross PP&E | C53: 9920 | D53: =C102 -> 9841 | E53: =D102 -> 9236 | F53: =E102 -> 10303 | G53: =F102 -> 9613 | H53: =G58 -> 10770.444
A54: + Capital Expenditure (CapEx) | C54: 1484 | D54: 1852 | E54: 2064 | F54: 2112 | G54: =G6*Assumptions!B13 -> 2214.8742 | H54: =H6*Assumptions!B13 -> 2325.6179
A55: Depreciation for the Year | C55: -1260 | D55: -1128 | E55: -1075 | F55: -1050 | G55: =-(G53*Assumptions!B14) -> -1057.43 | H55: =-(H53*Assumptions!B14) -> -1184.7489
A56: Accumulated Depreciation
A58: Closing PP&E (Net) → feeds BS + IS D&A | C58: =C53+C54+C55 -> 10144 | D58: =D53+D54+D55 -> 10565 | E58: =E53+E54+E55 -> 10225 | F58: =F53+F54+F55 -> 11365 | G58: =G53+G54+G55 -> 10770.444 | H58: =H53+H54+H55 -> 11911.313
A59: CapEx % of Revenue | C59: =C54/C6 -> 0.034508418 | D59: =D54/D6 -> 0.040477335 | E59: =E54/E6 -> 0.043857972 | F59: =F54/F6 -> 0.04405415 | G59: =G54/G6 -> 0.044 | H59: =H54/H6 -> 0.044
A61: DEBT SCHEDULE
A63: Opening Debt Balance | C63: 42761 | D63: =C117 -> 36377 | E63: =D117 -> 35547 | F63: =E117 -> 42375 | G63: =F117 -> 42119 | H63: =G66 -> 37119
A64: + New Debt Raised | C64: 3972 | D64: 6891 | E64: 12061 | F64: 4980 | G64: 0 | H64: 0
A65: - Debt Repaid | C65: -4930 | D65: -5034 | E65: -9533 | F65: -4967 | G65: =-Assumptions!B20 -> -5000 | H65: =-Assumptions!B20 -> -5000
A66: Closing Debt Balance → feeds BS | C66: =C63+C64+C65 -> 41803 | D66: =D63+D64+D65 -> 38234 | E66: =E63+E64+E65 -> 38075 | F66: =F63+F64+F65 -> 42388 | G66: =G63+G64+G65 -> 37119 | H66: =H63+H64+H65 -> 32119
A68: Average Debt Balance | C68: =(C63+C66)/2 -> 42282 | D68: =(D63+D66)/2 -> 37305.5 | E68: =(E63+E66)/2 -> 36811 | F68: =(F63+F66)/2 -> 42381.5 | G68: =(G63+G66)/2 -> 39619 | H68: =(H63+H66)/2 -> 34619
A69: Interest Expense → feeds IS | C69: =-(C68*Assumptions!B21) -> -1522.152 | D69: =-(D68*Assumptions!B21) -> -1342.998 | E69: =-(E68*Assumptions!B21) -> -1325.196 | F69: =-(F68*Assumptions!B21) -> -1525.734 | G69: =-(G68*Assumptions!B21) -> -1426.284 | H69: =-(H68*Assumptions!B21) -> -1246.284
A71: WORKING CAPITAL SCHEDULE
A73: AR = Revenue x DSO / 365 | C73: =C6*Assumptions!B16/365 -> 4123.6712 | D73: =D6*Assumptions!B16/365 -> 4387.3699 | E73: =E6*Assumptions!B16/365 -> 4512.6986 | F73: =F6*Assumptions!B16/365 -> 4597.0822 | G73: =G6*Assumptions!B16/365 -> 4826.9363 | H73: =H6*Assumptions!B16/365 -> 5068.2831
A74: Inventories = COGS x DIO / 365 | C74: =ABS(C8)*Assumptions!B17/365 -> 1824.6575 | D74: =ABS(D8)*Assumptions!B17/365 -> 1877.3699 | E74: =ABS(E8)*Assumptions!B17/365 -> 1857.5014 | F74: =ABS(F8)*Assumptions!B17/365 -> 1864.9014 | G74: =ABS(G8)*Assumptions!B17/365 -> 1964.5631 | H74: =ABS(H8)*Assumptions!B17/365 -> 2062.7912
A75: Accounts Payable = COGS x DPO / 365 | C75: =ABS(C8)*Assumptions!B18/365 -> 14794.521 | D75: =ABS(D8)*Assumptions!B18/365 -> 15221.918 | E75: =ABS(E8)*Assumptions!B18/365 -> 15060.822 | F75: =ABS(F8)*Assumptions!B18/365 -> 15120.822 | G75: =ABS(G8)*Assumptions!B18/365 -> 15928.89 | H75: =ABS(H8)*Assumptions!B18/365 -> 16725.334
A76: Net Working Capital (AR + Inv - AP) | C76: =C73+C74-C75 -> -8846.1918 | D76: =D73+D74-D75 -> -8957.1781 | E76: =E73+E74-E75 -> -8690.6219 | F76: =F73+F74-F75 -> -8658.8384 | G76: =G73+G74-G75 -> -9137.3904 | H76: =H73+H74-H75 -> -9594.2599
A78: Change in AR | D78: =-(D73-C96) -> -900.36986 | E78: =-(E73-D96) -> -1102.6986 | F78: =-(F73-E96) -> -1028.0822 | G78: =-(G73-F96) -> -1788.9363 | H78: =-(H73-G96) -> -241.34682
A79: Change in Inventories | D79: =-(D74-C97) -> 2355.6301 | E79: =-(E74-D97) -> 2566.4986 | F79: =-(F74-E97) -> 2863.0986 | G79: =-(G74-F97) -> 2460.4369 | H79: =-(H74-G97) -> -98.228154
A80: Change in AP | D80: =(D75-C111) -> -527.08219 | E80: =(E75-D111) -> -424.17808 | F80: =(F75-E111) -> -6591.1781 | G80: =(G75-F111) -> 1115.8898 | H80: =(H75-G111) -> 796.44449
A81: Change in NWC → feeds CF | C81: =IFERROR(C78+C79+C80,0) -> 0 | D81: =IFERROR(D78+D79+D80,0) -> 928.17808 | E81: =IFERROR(E78+E79+E80,0) -> 1039.6219 | F81: =IFERROR(F78+F79+F80,0) -> -4756.1616 | G81: =IFERROR(G78+G79+G80,0) -> 1787.3904 | H81: =IFERROR(H78+H79+H80,0) -> 456.86952
A82: Cash Conversion Cycle (days) | C82: =Assumptions!B16+Assumptions!B17-Assumptions!B18 -> -228 | D82: =Assumptions!B16+Assumptions!B17-Assumptions!B18 -> -228 | E82: =Assumptions!B16+Assumptions!B17-Assumptions!B18 -> -228 | F82: =Assumptions!B16+Assumptions!B17-Assumptions!B18 -> -228 | G82: =Assumptions!B16+Assumptions!B17-Assumptions!B18 -> -228 | H82: =Assumptions!B16+Assumptions!B17-Assumptions!B18 -> -228
A84: RETAINED EARNINGS SCHEDULE
A86: Opening Retained Earnings | C86: 69094 | D86: =C90 -> 71019 | E86: =D90 -> 73782 | F86: =E90 -> 76054 | G86: =F90 -> 80382 | H86: =G90 -> 83687.86
A87: + Net Profit (from IS) | C87: =C36 -> 7862 | D87: =D36 -> 8668 | E87: =E36 -> 8586 | F87: =F36 -> 11301 | G87: =G36 -> 13223.441 | H87: =H36 -> 13902.272
A88: - Dividends Paid | C88: -7616 | D88: -7990 | E88: -8333 | F88: -8718 | G88: =-(G43*G41) -> -9917.5811 | H88: =-(H43*H41) -> -10426.704
A89: +/- Other Equity Movements | C89: 0 | D89: 0 | E89: 0 | F89: 0 | G89: 0 | H89: 0
A90: Closing Retained Earnings → feeds BS | C90: 71019 | D90: 73782 | E90: 76054 | F90: 80382 | G90: =G86+G87+G88+G89 -> 83687.86 | H90: =H86+H87+H88+H89 -> 87163.428
A92: BALANCE SHEET
A94: Current Assets
A95: Cash (from CF Closing Cash) | C95: 11631 | D95: 13663 | E95: 14571 | F95: 15806 | G95: =G160 -> 0 | H95: =H160 -> -2208.4315
A96: Trade Receivables (from WC Schedule) | C96: 3487 | D96: 3410 | E96: 3569 | F96: 3038 | G96: =G73 -> 4826.9363 | H96: =H73 -> 5068.2831
A97: Inventories (from WC Schedule) | C97: 4233 | D97: 4424 | E97: 4728 | F97: 4425 | G97: =G74 -> 1964.5631 | H97: =H74 -> 2062.7912
A98: Other Current Assets | C98: 3240 | D98: 5235 | E98: 3129 | F98: 7775 | G98: =F98 -> 7775 | H98: =G98 -> 7775
A99: Total Current Assets | C99: =C95+C96+C97+C98 -> 22591 | D99: =D95+D96+D97+D98 -> 26732 | E99: =E95+E96+E97+E98 -> 25997 | F99: =F95+F96+F97+F98 -> 31044 | G99: =G95+G96+G97+G98 -> 14566.499 | H99: =H95+H96+H97+H98 -> 12697.643
A101: Non-Current Assets
A102: PP&E Net (from PP&E Schedule) | C102: 9841 | D102: 9236 | E102: 10303 | F102: 9613 | G102: =G58 -> 10770.444 | H102: =H58 -> 11911.313
A103: Goodwill | C103: 18782 | D103: 18358 | E103: 18139 | F103: 15491 | G103: =F103 -> 15491 | H103: =G103 -> 15491
A104: Other Intangibles | C104: 14849 | D104: 14349 | E104: 13301 | F104: 12531 | G104: =F104 -> 12531 | H104: =G104 -> 12531
A105: Investments & Other | C105: 26700 | D105: 29028 | E105: 32809 | F105: 36137 | G105: =F105 -> 36137 | H105: =G105 -> 36137
A106: Total Non-Current Assets | C106: =C102+C103+C104+C105 -> 70172 | D106: =D102+D103+D104+D105 -> 70971 | E106: =E102+E103+E104+E105 -> 74552 | F106: =F102+F103+F104+F105 -> 73772 | G106: =G102+G103+G104+G105 -> 74929.444 | H106: =H102+H103+H104+H105 -> 76070.313
A108: TOTAL ASSETS | C108: =C99+C106 -> 92763 | D108: =D99+D106 -> 97703 | E108: =E99+E106 -> 100549 | F108: =F99+F106 -> 104816 | G108: =G99+G106 -> 89495.944 | H108: =H99+H106 -> 88767.956
A110: Current Liabilities
A111: Trade Payables (from WC Schedule) | C111: 15749 | D111: 15485 | E111: 21712 | F111: 14813 | G111: =G75 -> 15928.89 | H111: =H75 -> 16725.334
A112: Short-term Borrowings | C112: 2772 | D112: 6517 | E112: 2147 | F112: 3373 | G112: =F112 -> 3373 | H112: =G112 -> 3373
A113: Other Current Liabilities | C113: 1203 | D113: 1569 | E113: 1390 | F113: 3095 | G113: =F113 -> 3095 | H113: =G113 -> 3095
A114: Total Current Liabilities | C114: =C111+C112+C113 -> 19724 | D114: =D111+D112+D113 -> 23571 | E114: =E111+E112+E113 -> 25249 | F114: =F111+F112+F113 -> 21281 | G114: =G111+G112+G113 -> 22396.89 | H114: =H111+H112+H113 -> 23193.334
A116: Non-Current Liabilities
A117: Long-term Debt (from Debt Schedule) | C117: 36377 | D117: 35547 | E117: 42375 | F117: 42119 | G117: =G66 -> 37119 | H117: =H66 -> 32119
A118: Pensions & Post-Retirement | C118: 2336 | D118: 1765 | E118: 1661 | F118: 1664 | G118: =F118 -> 1664 | H118: =G118 -> 1664
A119: Other Non-Current Liabilities | C119: 8500 | D119: 9340 | E119: 4892 | F119: 5477 | G119: =F119 -> 5477 | H119: =G119 -> 5477
A120: Total Non-Current Liabilities | C120: =C117+C118+C119 -> 47213 | D120: =D117+D118+D119 -> 46652 | E120: =E117+E118+E119 -> 48928 | F120: =F117+F118+F119 -> 49260 | G120: =G117+G118+G119 -> 44260 | H120: =H117+H118+H119 -> 39260
A122: TOTAL LIABILITIES | C122: =C114+C120 -> 66937 | D122: =D114+D120 -> 70223 | E122: =E114+E120 -> 74177 | F122: =F114+F120 -> 70541 | G122: =G114+G120 -> 66656.89 | H122: =H114+H120 -> 62453.334
A124: Equity
A125: Share Capital & Premium | C125: 20582 | D125: 20969 | E125: 21561 | F125: 22341 | G125: =F125 -> 22341 | H125: =G125 -> 22341
A126: Retained Earnings (from RE Schedule) | C126: =C90 -> 71019 | D126: =D90 -> 73782 | E126: =E90 -> 76054 | F126: =F90 -> 80382 | G126: =G90 -> 83687.86 | H126: =H90 -> 87163.428
A127: Other Reserves (treasury stock + AOCI + buybacks) | C127: -67496 | D127: -68810 | E127: -72759 | F127: -70554 | G127: =F127+G154 -> -85295.807 | H127: =G127+H154 -> -85295.807
A128: Non-Controlling Interests | C128: 1721 | D128: 1539 | E128: 1516 | F128: 2106 | G128: =F128 -> 2106 | H128: =G128 -> 2106
A129: TOTAL EQUITY | C129: =C125+C126+C127+C128 -> 25826 | D129: =D125+D126+D127+D128 -> 27480 | E129: =E125+E126+E127+E128 -> 26372 | F129: =F125+F126+F127+F128 -> 34275 | G129: =G125+G126+G127+G128 -> 22839.054 | H129: =H125+H126+H127+H128 -> 26314.622
A131: TOTAL LIABILITIES + EQUITY | C131: =C122+C129 -> 92763 | D131: =D122+D129 -> 97703 | E131: =E122+E129 -> 100549 | F131: =F122+F129 -> 104816 | G131: =G122+G129 -> 89495.944 | H131: =H122+H129 -> 88767.956
A133: Balance Check (must equal 0) | C133: =C108-C131 -> 0 | D133: =D108-D131 -> 0 | E133: =E108-E131 -> 0 | F133: =F108-F131 -> 0 | G133: =G108-G131 -> 0 | H133: =H108-H131 -> 0
A135: CASH FLOW STATEMENT
A137: Operating Activities
A138: Net Profit (from IS) | C138: =C36 -> 7862 | D138: =D36 -> 8668 | E138: =E36 -> 8586 | F138: =F36 -> 11301 | G138: =G36 -> 13223.441 | H138: =H36 -> 13902.272
A139: + D&A (from PP&E Schedule) | C139: =-C55 -> 1260 | D139: =-D55 -> 1128 | E139: =-E55 -> 1075 | F139: =-F55 -> 1050 | G139: =-G55 -> 1057.43 | H139: =-H55 -> 1184.7489
...
